repo2md/__init__.py
repo2md/config.py
repo2md/github.py
repo2md/main.py
repo2md/tree.py
repo2md/utils.py
repo2md-0.2.0.dist-info/licenses/LICENSE
repo2md-0.2.0.dist-info/METADATA
repo2md-0.2.0.dist-info/WHEEL
repo2md-0.2.0.dist-info/entry_points.txt
repo2md-0.2.0.dist-info/top_level.txt
repo2md-0.2.0.dist-info/RECORD
