Metadata-Version: 2.4
Name: repo2md
Version: 0.2.0
Summary: Python module to convert GitHub repositories to markdown files.
Author-email: Vignesh Rao <svignesh1793@gmail.com>
Project-URL: Homepage, https://github.com/thevickypedia/repo2md
Project-URL: Source, https://github.com/thevickypedia/repo2md
Project-URL: Bug Tracker, https://github.com/thevickypedia/repo2md/issues
Project-URL: Release Notes, https://github.com/thevickypedia/repo2md/blob/main/release_notes.rst
Keywords: repo2md
Classifier: Development Status :: 5 - Production/Stable
Classifier: Programming Language :: Python :: 3
Requires-Python: >=3.10
License-File: LICENSE
Requires-Dist: click==8.*
Requires-Dist: python-dotenv==1.*
Requires-Dist: requests==2.*
Provides-Extra: dev
Requires-Dist: pre-commit; extra == "dev"
Requires-Dist: gitverse; extra == "dev"
Dynamic: license-file
